<?xml version='1.0' encoding='UTF-8'?>
<setting>
 <root Name="كتب علمية" id="0">
  <Item Name="كتب كمبيتر" id="29"/>
  <Item Name="بحوث ومسائل مالية واقتصادية" id="20"/>
  <Item Name="الإسلام والطب" id="10"/>
 </root>
 <root Name="كتب التاريخ والبلدان والتراجم" id="1">
  <Item Name="كتب التاريخ" id="13"/>
  <Item Name="كتب البلدان" id="16"/>
  <Item Name="كتب الأنساب" id="17"/>
  <Item Name="تراجم وطبقات" id="12"/>
 </root>
 <root Name="كتب الأدب واللغة والمعاجم" id="2">
  <Item Name="منظومات" id="49"/>
  <Item Name="ملحق علوم اللغة والمعاجم" id="27"/>
  <Item Name="معاجم وكتب اللغات الأخرى" id="23"/>
  <Item Name="كتب عامة" id="33"/>
  <Item Name="كتب الأدب" id="18"/>
  <Item Name="فهارس الكتب" id="6"/>
  <Item Name="علوم لغة ومعاجم" id="5"/>
  <Item Name="دواوين الشعر" id="9"/>
 </root>
 <root Name="الكتب الشرعية" id="3">
  <Item Name="ملحق الفقه المالكي" id="34"/>
  <Item Name="ملحق الفقه الشافعي" id="36"/>
  <Item Name="ملحق الفقه الحنفي" id="32"/>
  <Item Name="ملحق الفقه الحنبلي" id="31"/>
  <Item Name="ملحق السيرة والشمائل" id="44"/>
  <Item Name="ملحق التفاسير" id="24"/>
  <Item Name="ملحق الأجزاء الحديثية" id="46"/>
  <Item Name="ملحق أصول وقواعد الفقه" id="40"/>
  <Item Name="مصطلح الحديث" id="51"/>
  <Item Name="مسائل فقهية وفتاوى" id="1"/>
  <Item Name="كتب المتون" id="19"/>
  <Item Name="كتب العلل والسؤالات" id="7"/>
  <Item Name="كتب التخريج" id="50"/>
  <Item Name="كتب الأخلاق والرقاق" id="11"/>
  <Item Name="كتب ابن تيمية" id="22"/>
  <Item Name="كتب ابن القيم" id="21"/>
  <Item Name="كتب ابن أبي الدنيا" id="25"/>
  <Item Name="فقه مالكي" id="38"/>
  <Item Name="فقه عام وفتاوى" id="43"/>
  <Item Name="فقه شافعي" id="39"/>
  <Item Name="فقه حنفي" id="35"/>
  <Item Name="فقه حنبلي" id="41"/>
  <Item Name="علوم القرآن" id="8"/>
  <Item Name="شروح الحديث" id="2"/>
  <Item Name="الملل و النحل" id="3"/>
  <Item Name="الفتن وأشراط الساعة" id="26"/>
  <Item Name="العقيدة" id="14"/>
  <Item Name="السيرة والشمائل" id="4"/>
  <Item Name="السياسة الشرعية والقضاء" id="48"/>
  <Item Name="الرقى الشرعية" id="15"/>
  <Item Name="الرسائل والمسائل النجدية" id="99"/>
  <Item Name="التفاسير" id="28"/>
  <Item Name="الأجزاء حديثية" id="46"/>
  <Item Name="أصول الفقه" id="47"/>
 </root>
</setting>
